al_microsoft_teams/__init__.py
al_microsoft_teams/teams.py
al_microsoft_teams-1.0.5.dist-info/LICENSE
al_microsoft_teams-1.0.5.dist-info/METADATA
al_microsoft_teams-1.0.5.dist-info/WHEEL
al_microsoft_teams-1.0.5.dist-info/top_level.txt
al_microsoft_teams-1.0.5.dist-info/RECORD
